fritm/__init__.py
fritm/hook.py
fritm/proxy.py
fritm/script.js
fritm-0.4.1.dist-info/LICENSE
fritm-0.4.1.dist-info/METADATA
fritm-0.4.1.dist-info/WHEEL
fritm-0.4.1.dist-info/entry_points.txt
fritm-0.4.1.dist-info/top_level.txt
fritm-0.4.1.dist-info/RECORD
