Metadata-Version: 2.1
Name: fritm
Version: 0.4.1
Summary: Minimalist and cross-platform network reverse engineering framework
Home-page: https://github.com/louisabraham/fritm
Author: Louis Abraham
Author-email: louis.abraham@yahoo.fr
License: MIT
Platform: UNKNOWN
Classifier: Topic :: Internet :: Proxy Servers
Classifier: Topic :: Internet :: WWW/HTTP
Classifier: Topic :: Security
Requires-Python: >=3.5
